{
  "type": "minecraft:crafting_shaped",
  "pattern": [
    "SBS",
    "NAN",
    " S "
  ],
  "key": {
    "S": [
      {
        "item": "minecraft:stick"
      }
    ],
    "B": [
      {
        "item": "unicopia:burned_juice"
      }
    ],
    "N": [
      {
	    "item": "minecraft:iron_nugget"
      }
    ],
    "A": [
      {
	    "item": "minecraft:apple",
	    "data": 0
      },
      {
  	    "item": "minecraft:apple",
  	    "data": 1
      },
      {
	    "item": "minecraft:apple",
	    "data": 2
      },
      {
	    "item": "minecraft:apple",
	    "data": 3
      }
    ]
  },
  "result": {
    "item": "unicopia:apple_cider",
    "data": 0,
    "count": 1
  }
}
