{
  "parent": "unicopia:unicopia/unicorn/magical_route",
  "display": {
    "icon": {
      "item": "unicopia:spellbook"
    },
    "title": {
      "translate": "advancements.unicopia.books.title"
    },
    "description": {
      "translate": "advancements.unicopia.books.description"
    },
    "frame": "task",
    "show_toast": true,
    "announce_to_chat": true,
    "hidden": false
  },
  "criteria": {
    "has_book": {
      "trigger": "minecraft:inventory_changed",
      "conditions": {
        "items": [
          { "items": [ "unicopia:spellbook" ] }
        ]
      }
    }
  },
  "requirements": [
    [ "has_book" ]
  ]
}
